edx_sysadmin/__init__.py
edx_sysadmin/apps.py
edx_sysadmin/forms.py
edx_sysadmin/git_import.py
edx_sysadmin/models.py
edx_sysadmin/urls.py
edx_sysadmin/views.py
edx_sysadmin/api/__init__.py
edx_sysadmin/api/permissions.py
edx_sysadmin/api/urls.py
edx_sysadmin/api/views.py
edx_sysadmin/conf/locale/config.yaml
edx_sysadmin/management/__init__.py
edx_sysadmin/management/commands/__init__.py
edx_sysadmin/management/commands/git_add_course.py
edx_sysadmin/migrations/0001_course_git_log.py
edx_sysadmin/migrations/0002_alter_coursegitlog_course_import_log.py
edx_sysadmin/migrations/__init__.py
edx_sysadmin/settings/common.py
edx_sysadmin/static/edx_sysadmin/css/style.css
edx_sysadmin/static/edx_sysadmin/js/course.js
edx_sysadmin/templates/edx_sysadmin/base.html
edx_sysadmin/templates/edx_sysadmin/courses.html
edx_sysadmin/templates/edx_sysadmin/gitimport.html
edx_sysadmin/templates/edx_sysadmin/gitlogs.html
edx_sysadmin/templates/edx_sysadmin/gitlogs_pagination.html
edx_sysadmin/templates/edx_sysadmin/users.html
edx_sysadmin/templatetags/__init__.py
edx_sysadmin/templatetags/sysadmin_extras.py
edx_sysadmin/utils/__init__.py
edx_sysadmin/utils/markup.py
edx_sysadmin/utils/utils.py
edx_sysadmin-0.4.0.dist-info/METADATA
edx_sysadmin-0.4.0.dist-info/WHEEL
edx_sysadmin-0.4.0.dist-info/entry_points.txt
edx_sysadmin-0.4.0.dist-info/licenses/LICENSE.txt
edx_sysadmin-0.4.0.dist-info/RECORD
