Metadata-Version: 2.4
Name: edx-sysadmin
Version: 0.4.0
Summary: An Open edX plugin to enable SysAdmin panel
Author: MIT Office of Digital Learning
License-Expression: BSD-3-Clause
License-File: LICENSE.txt
Keywords: Python,edx
Requires-Python: >=3.11
Requires-Dist: django>=4.0
Requires-Dist: djangorestframework>=3.14.0
Requires-Dist: edx-django-utils>4.0.0
Requires-Dist: edx-drf-extensions>=10.0.0
Requires-Dist: edx-opaque-keys
